tests/__init__.py
tests/test_parallel_search.py
tests/test_ph_plot_basic.py
tests/test_ph_plot_plotly.py
tests/test_ph_plot_v2.py
tests/test_ph_plot_v3.py
thermodynamics/__init__.py
thermodynamics/parallel_search.py
thermodynamics/ph_plot_basic.py
thermodynamics/ph_plot_plotly.py
thermodynamics/ph_plot_v2.py
thermodynamics/ph_plot_v3.py
thermodynamics_mrh335-0.2.0.dist-info/licenses/LICENSE
thermodynamics_mrh335-0.2.0.dist-info/METADATA
thermodynamics_mrh335-0.2.0.dist-info/WHEEL
thermodynamics_mrh335-0.2.0.dist-info/top_level.txt
thermodynamics_mrh335-0.2.0.dist-info/RECORD
