Metadata-Version: 2.4
Name: thermodynamics-mrh335
Version: 0.2.0
Summary: A Python package for thermodynamic calculations
Home-page: https://github.com/mrh335/thermodynamics
Author: Mark Hoehne
Author-email: your.email@example.com
Classifier: Programming Language :: Python :: 3
Classifier: License :: OSI Approved :: MIT License
Classifier: Operating System :: OS Independent
Requires-Python: >=3.7
License-File: LICENSE
Dynamic: author
Dynamic: author-email
Dynamic: classifier
Dynamic: description
Dynamic: description-content-type
Dynamic: home-page
Dynamic: license-file
Dynamic: requires-python
Dynamic: summary
